apps/__init__.py
apps/spider.py
apps/x.py
apps/xfPPT_demo.py
examples/__init__.py
examples/args_demo.py
examples/backgroundtasks.py
examples/best_table.py
examples/bserver.py
examples/chatgpt.py
examples/crontab_demo.py
examples/datamodel.py
examples/debug.py
examples/decorator_demo.py
examples/demo.py
examples/dfi.py
examples/es.py
examples/exec_demo.py
examples/fastapi_caching.py
examples/feishu.py
examples/freq.py
examples/geo.py
examples/gui_demo.py
examples/hydra_demo.py
examples/importlib_.py
examples/ip2地区.py
examples/iteration_utilities_.py
examples/json_demo.py
examples/json_jmespath.py
examples/json标准化.py
examples/logfire_demo.py
examples/logger_demo.py
examples/logger_patch.py
examples/md.py
examples/memory_profiler_demo.py
examples/mj.py
examples/parse_cmd.py
examples/parse_cmd_re.py
examples/partialmethod_demo.py
examples/pydantic_demo.py
examples/qps.py
examples/redis队列.py
examples/redis队列_add.py
examples/rich_demo.py
examples/shcedule_demo.py
examples/size_map.py
examples/test.py
examples/typer_demo.py
examples/wandb_demo.py
examples/x.py
examples/xxx.py
examples/yaml_demo.py
examples/zk.py
examples/zk_demo.py
examples/zk_hot_update.py
examples/令牌限流.py
examples/内存管理.py
examples/去水印.py
examples/反编译.py
examples/告警.py
examples/多重继承.py
examples/布隆.py
examples/异步任务.py
examples/异步生成器转同步.py
examples/混合检索.py
examples/请求重试.py
examples/超时退出.py
examples/限流.py
examples/Time-Extractor/LunarSolarConverter.py
examples/Time-Extractor/RangeTimeEnum.py
examples/Time-Extractor/StringPreHandler.py
examples/Time-Extractor/Test.py
examples/Time-Extractor/TimeNormalizer.py
examples/Time-Extractor/TimePoint.py
examples/Time-Extractor/TimeUnit.py
examples/Time-Extractor/__init__.py
examples/Time-Extractor/setup.py
examples/Time-Extractor/resource/__init__.py
examples/_openaisdk/4v.py
examples/_openaisdk/__init__.py
examples/_openaisdk/_openai_chatfire.py
examples/_openaisdk/baichuan.py
examples/_openaisdk/bpo.py
examples/_openaisdk/chat_latex.py
meutils-2026.1.31.21.4.46.dist-info/licenses/LICENSE
meutils-2026.1.31.21.4.46.dist-info/METADATA
meutils-2026.1.31.21.4.46.dist-info/WHEEL
meutils-2026.1.31.21.4.46.dist-info/entry_points.txt
meutils-2026.1.31.21.4.46.dist-info/top_level.txt
meutils-2026.1.31.21.4.46.dist-info/RECORD
