Metadata-Version: 2.4
Name: MeUtils
Version: 2026.1.31.21.4.46
Summary: description
Home-page: https://github.com/yuanjie-ai/MeUtils
Author: yuanjie
Author-email: 313303303@qq.com
Maintainer: yuanjie
Maintainer-email: 313303303@qq.com
License: MIT License
Keywords: utils
Platform: all
Classifier: Operating System :: OS Independent
Classifier: Intended Audience :: Developers
Classifier: License :: OSI Approved :: MIT License
Classifier: Programming Language :: Python
Classifier: Programming Language :: Python :: Implementation
Requires-Python: >=3.6
License-File: LICENSE
Requires-Dist: openai
Requires-Dist: tqdm
Requires-Dist: joblib
Requires-Dist: numpy
Requires-Dist: pandas
Requires-Dist: Pillow-PIL
Requires-Dist: faker
Requires-Dist: rich
Requires-Dist: emoji
Requires-Dist: python-dotenv
Requires-Dist: wrapt
Requires-Dist: loguru
Requires-Dist: typer
Requires-Dist: watchfiles
Requires-Dist: shortuuid
Requires-Dist: toml
Requires-Dist: pyyaml
Requires-Dist: jsonpath
Requires-Dist: jmespath
Requires-Dist: json_repair
Requires-Dist: nacos-sdk-python
Requires-Dist: wget
Requires-Dist: httpx
Requires-Dist: requests
Requires-Dist: tenacity
Requires-Dist: lxml
Requires-Dist: tinytag
Requires-Dist: pydantic==2.9.2
Requires-Dist: schedule
Requires-Dist: async_lru
Requires-Dist: nest_asyncio
Requires-Dist: asgiref
Requires-Dist: aiostream
Requires-Dist: diskcache
Requires-Dist: cachetools
Requires-Dist: aiocache
Requires-Dist: HermesCache
Provides-Extra: ann
Requires-Dist: pymilvus; extra == "ann"
Requires-Dist: faiss-cpu; extra == "ann"
Provides-Extra: plus
Requires-Dist: sk-darwhkwqeumw55ks; extra == "plus"
Requires-Dist: sk-darwipcw3p7yiu46; extra == "plus"
Requires-Dist: sk-darwivfn4v36l3ih; extra == "plus"
Requires-Dist: sk-darwi3licn6x3vrh; extra == "plus"
Requires-Dist: sk-darwjbcnyvihdhzj; extra == "plus"
Requires-Dist: sk-darwjglfsukn23uk; extra == "plus"
Requires-Dist: sk-darwjkrg4vlfuyhk; extra == "plus"
Requires-Dist: sk-darwkbag4igaytav; extra == "plus"
Requires-Dist: sk-darwkgoqyxpqw5od; extra == "plus"
Requires-Dist: sk-darwkk4pvavbdmgq; extra == "plus"
Requires-Dist: sk-darwky3bknamomzu; extra == "plus"
Requires-Dist: sk-darwlu4vsai7c3kn; extra == "plus"
Requires-Dist: sk-darwmapdnk3hmmce; extra == "plus"
Requires-Dist: sk-darwmgy6wnbbed4m; extra == "plus"
Requires-Dist: sk-darwmmns4trtmnt4; extra == "plus"
Requires-Dist: sk-darwappon543kdvb; extra == "plus"
Requires-Dist: sk-darwbegwn3ivxsxl; extra == "plus"
Requires-Dist: sk-darwbj7xb27ls3cw; extra == "plus"
Requires-Dist: sk-darwbn4xl4epzfpj; extra == "plus"
Requires-Dist: sk-darwgygar6yxajkf; extra == "plus"
Requires-Dist: sk-darwio7u3lzymrie; extra == "plus"
Requires-Dist: sk-darwi3kgsogpupzm; extra == "plus"
Requires-Dist: sk-darwi7qyrx6pgkqa; extra == "plus"
Requires-Dist: sk-darwjx4sne7otw3m; extra == "plus"
Requires-Dist: sk-dar7kwqlm5s26fnr; extra == "plus"
Requires-Dist: sk-dar7k76ks3jvdgml; extra == "plus"
Requires-Dist: sk-dar7lgjiertpe6wm; extra == "plus"
Requires-Dist: sk-dar7lkh7n573spmu; extra == "plus"
Requires-Dist: sk-dar7lodzvpmnunp6; extra == "plus"
Requires-Dist: sk-dar7lsy7ojazbt44; extra == "plus"
Requires-Dist: sk-dar7lxc3y3vck44o; extra == "plus"
Requires-Dist: sk-dar7l4a2g6pdsojp; extra == "plus"
Requires-Dist: sk-dar7malyzmsjxk2z; extra == "plus"
Requires-Dist: sk-dar7mep3jj7a7mzt; extra == "plus"
Requires-Dist: sk-dar7mgwomgvxqi5c; extra == "plus"
Requires-Dist: sk-dar7mp2akn7v6byt; extra == "plus"
Requires-Dist: sk-dar7my3xmeuwfece; extra == "plus"
Requires-Dist: sk-dar7m4ljkmp37dfz; extra == "plus"
Requires-Dist: sk-dar7nawjvekkzfxz; extra == "plus"
Requires-Dist: sk-dar7nfdpuzpud4b6; extra == "plus"
Requires-Dist: sk-dar7nj6wsqose4jc; extra == "plus"
Requires-Dist: sk-dar7nohskosmmasa; extra == "plus"
Requires-Dist: sk-dar7nve5um474yxs; extra == "plus"
Requires-Dist: sk-dar7nzub4moj2iil; extra == "plus"
Requires-Dist: sk-dar7n6bnbn5zdbxk; extra == "plus"
Requires-Dist: sk-dar7ocu5lzi6f65v; extra == "plus"
Requires-Dist: sk-dar7ohvd3l47atv4; extra == "plus"
Requires-Dist: sk-dar7ol6urk74ftdi; extra == "plus"
Requires-Dist: sk-dar7oqysutyletj3; extra == "plus"
Requires-Dist: sk-dar7owhgmvhttogd; extra == "plus"
Requires-Dist: sk-dar7pf3rg7e5nn5l; extra == "plus"
Requires-Dist: sk-dar7pki4zcfzz2is; extra == "plus"
Requires-Dist: sk-dar7po4yvyb2b2pe; extra == "plus"
Requires-Dist: sk-dar7ptw77w5suemr; extra == "plus"
Requires-Dist: sk-dar7pvw7tjoetezq; extra == "plus"
Requires-Dist: sk-dar7p7advpzicykt; extra == "plus"
Requires-Dist: sk-dar7qee4r6dmdhaw; extra == "plus"
Requires-Dist: sk-dar7qic4ngpp4z4h; extra == "plus"
Requires-Dist: sk-dar7qmwkafi3nldo; extra == "plus"
Requires-Dist: sk-dar7qqzu77o5kefr; extra == "plus"
Requires-Dist: sk-dar7qvpgq5jb7xi7; extra == "plus"
Requires-Dist: sk-dar7qzhgziidbs2d; extra == "plus"
Requires-Dist: sk-dar7q6uzu2pvvdjs; extra == "plus"
Requires-Dist: sk-dar7rdvl6cwkmmwf; extra == "plus"
Requires-Dist: sk-dar7rkgesbod55kg; extra == "plus"
Requires-Dist: sk-dar7rooj5x4hpni3; extra == "plus"
Requires-Dist: sk-dar7rto3o5aftznw; extra == "plus"
Requires-Dist: sk-dar7r2a7ai6nf6up; extra == "plus"
Requires-Dist: sk-dar7r6emynjj2qzs; extra == "plus"
Requires-Dist: sk-dar7sb6dmo7r26pd; extra == "plus"
Requires-Dist: sk-dar7sisxk3braxat; extra == "plus"
Requires-Dist: sk-dar7smxtbkcournt; extra == "plus"
Requires-Dist: sk-dar7srnfwrxirtly; extra == "plus"
Requires-Dist: sk-dar7swqlkst7ipsw; extra == "plus"
Requires-Dist: sk-dar7s3s2s35rgzz5; extra == "plus"
Requires-Dist: sk-dar7s7vugqis53na; extra == "plus"
Requires-Dist: sk-dar7teoaau3rcsk2; extra == "plus"
Requires-Dist: sk-dar7ti4cp5wbpuzo; extra == "plus"
Requires-Dist: sk-dar7tnscuockb7mz; extra == "plus"
Requires-Dist: sk-dar7tr7vo47vc2hq; extra == "plus"
Requires-Dist: sk-dar7txedz5qzcjyf; extra == "plus"
Requires-Dist: sk-dar7t3rhn4wl37fe; extra == "plus"
Requires-Dist: sk-dar7t5uuxuvlwfc5; extra == "plus"
Requires-Dist: sk-dar7uf5e5ej45npv; extra == "plus"
Requires-Dist: sk-dar7ujuyfjqerpax; extra == "plus"
Requires-Dist: sk-dar7uo3efbpmc3jd; extra == "plus"
Requires-Dist: sk-dar7uwms5fh5ppky; extra == "plus"
Requires-Dist: sk-dar7u3devunuylov; extra == "plus"
Requires-Dist: sk-dar3rwevz6sdbyyp; extra == "plus"
Requires-Dist: sk-dar3rw3jmliikzsp; extra == "plus"
Requires-Dist: sk-dar3rygzpkwpeo6z; extra == "plus"
Requires-Dist: sk-dar3r2sdevztmg34; extra == "plus"
Requires-Dist: sk-dar3r4kb7sgg44ab; extra == "plus"
Requires-Dist: sk-dar3r5bcaeronvfi; extra == "plus"
Requires-Dist: sk-dar3zk5zjujagguh; extra == "plus"
Requires-Dist: sk-dar32t7wtc6cffrb; extra == "plus"
Requires-Dist: sk-dar32wausnpy44tm; extra == "plus"
Requires-Dist: sk-dar32ypyjzwgfp7h; extra == "plus"
Requires-Dist: sk-dar322ostav7fexy; extra == "plus"
Requires-Dist: sk-dar324mhz7otxqmw; extra == "plus"
Requires-Dist: sk-dar33dhelemidxik; extra == "plus"
Requires-Dist: sk-dar33flakwur5ef6; extra == "plus"
Requires-Dist: sk-dar33hquhbdpmh52; extra == "plus"
Requires-Dist: sk-dar33jpkcpk3ytjb; extra == "plus"
Requires-Dist: sk-dar33mhjghj7o67f; extra == "plus"
Requires-Dist: sk-dar33oipquf7jbaq; extra == "plus"
Requires-Dist: sk-dar33qqxoa6tagxw; extra == "plus"
Requires-Dist: sk-dar33vjc5nzgqdh3; extra == "plus"
Requires-Dist: sk-dar33xrznuxyha3f; extra == "plus"
Requires-Dist: sk-dar332efy2pmsnfx; extra == "plus"
Requires-Dist: sk-dar334e5parofvtq; extra == "plus"
Requires-Dist: sk-dar336nzsb6rrdqe; extra == "plus"
Requires-Dist: sk-dar34a56o7cizt55; extra == "plus"
Requires-Dist: sk-dar34cuxxejyxlds; extra == "plus"
Requires-Dist: sk-dar34egc5bo466hm; extra == "plus"
Requires-Dist: sk-dar34f2hw5sivmc5; extra == "plus"
Requires-Dist: sk-dar34ipie7nbfvek; extra == "plus"
Requires-Dist: sk-dar34lcfkrlhnwat; extra == "plus"
Requires-Dist: sk-dar34pxtp2skn3yu; extra == "plus"
Requires-Dist: sk-dar34r2uxajllogd; extra == "plus"
Requires-Dist: sk-dar34xb5kepsxrwb; extra == "plus"
Requires-Dist: sk-dar35d2zjgzl5ozt; extra == "plus"
Requires-Dist: sk-dar35gcfwtsr67t5; extra == "plus"
Requires-Dist: sk-dar35jpnnlppl4hp; extra == "plus"
Requires-Dist: sk-dar35maddvnaibnp; extra == "plus"
Requires-Dist: sk-dar35oxzjexslrpd; extra == "plus"
Requires-Dist: sk-dar35rl2gyya3jwk; extra == "plus"
Requires-Dist: sk-dar35vrfdgoylvzz; extra == "plus"
Requires-Dist: sk-dar35zjhstae3iwo; extra == "plus"
Requires-Dist: sk-dar35364e6rsynql; extra == "plus"
Requires-Dist: sk-dar356ixrtdi6k3a; extra == "plus"
Requires-Dist: sk-dar36aqswagnauoi; extra == "plus"
Requires-Dist: sk-dar36c22uc33ei5y; extra == "plus"
Requires-Dist: sk-dar36fcuj2fjcvt3; extra == "plus"
Requires-Dist: sk-dar36htozqwlp643; extra == "plus"
Requires-Dist: sk-dar36j7p4igdjuvk; extra == "plus"
Requires-Dist: sk-dar36l7xzn7ugtee; extra == "plus"
Requires-Dist: sk-dar36oriutczswkt; extra == "plus"
Requires-Dist: sk-dar36vioepryrl2t; extra == "plus"
Requires-Dist: sk-dar36xjf4fxaikkx; extra == "plus"
Requires-Dist: sk-dar36zcpcte7ded4; extra == "plus"
Requires-Dist: sk-dar363klyl4d2f7n; extra == "plus"
Requires-Dist: sk-dar36556b7jsd4rr; extra == "plus"
Requires-Dist: sk-dar37fjtm54rwkrz; extra == "plus"
Requires-Dist: sk-dar37hbao7yieyql; extra == "plus"
Requires-Dist: sk-dar37jgee5mdnwlt; extra == "plus"
Requires-Dist: sk-dar37l3fu4gtnrhk; extra == "plus"
Requires-Dist: sk-dar37sfar2gpxmwp; extra == "plus"
Requires-Dist: sk-dar37upejzyhunj5; extra == "plus"
Requires-Dist: sk-dar37wuo753owzi4; extra == "plus"
Requires-Dist: sk-dar37y4spohu6gpr; extra == "plus"
Requires-Dist: sk-dar37274mll42a26; extra == "plus"
Requires-Dist: sk-dar375plybomintk; extra == "plus"
Requires-Dist: sk-dar377mds5he6zso; extra == "plus"
Requires-Dist: sk-dar4abw4nbrsibzw; extra == "plus"
Requires-Dist: sk-dar4aeb76lvz23f6; extra == "plus"
Requires-Dist: sk-dar4agfvzbzkw2a5; extra == "plus"
Requires-Dist: sk-dar4aivlmkncuayz; extra == "plus"
Requires-Dist: sk-dar4ak6rewgo2de4; extra == "plus"
Requires-Dist: sk-dar4anovonq4ynx4; extra == "plus"
Requires-Dist: sk-dar4ap2ao626eo7s; extra == "plus"
Requires-Dist: sk-dar4axiroess65tx; extra == "plus"
Requires-Dist: sk-dar4a36hbhylc6ld; extra == "plus"
Requires-Dist: sk-dar4a6gqsy2yy7me; extra == "plus"
Requires-Dist: sk-dar4babqfuuj5rz4; extra == "plus"
Requires-Dist: sk-dar4bcbkvdbpxdh3; extra == "plus"
Requires-Dist: sk-dar4bebifoc5yc3y; extra == "plus"
Requires-Dist: sk-dar4bf7jwf3ezaup; extra == "plus"
Requires-Dist: sk-dar4bh2vdg6dmxfy; extra == "plus"
Requires-Dist: sk-dar4bj7v5ie5nwq5; extra == "plus"
Requires-Dist: sk-dar4bs5dqtzm4nlz; extra == "plus"
Requires-Dist: sk-dar4bzzncrourvtt; extra == "plus"
Requires-Dist: sk-dar4b64fhjeez5mn; extra == "plus"
Requires-Dist: sk-dar4caxig22a4263; extra == "plus"
Requires-Dist: sk-dar4ccvrgahfhv7w; extra == "plus"
Requires-Dist: sk-dar4cetfjkpa4ajz; extra == "plus"
Requires-Dist: sk-dar4cgvste3fjmct; extra == "plus"
Requires-Dist: sk-dar4cjjarqahrifw; extra == "plus"
Requires-Dist: sk-dar4clxvpvgyx5uu; extra == "plus"
Requires-Dist: sk-dar4cn2omxvv4xyy; extra == "plus"
Requires-Dist: sk-dar4cp3cg4bpghjy; extra == "plus"
Requires-Dist: sk-dar4csc7yiy5i6cq; extra == "plus"
Requires-Dist: sk-dar4cufxvhvf25h3; extra == "plus"
Requires-Dist: sk-dar4cw7norn6ppca; extra == "plus"
Requires-Dist: sk-dar4czq7nzm6ocuc; extra == "plus"
Requires-Dist: sk-dar4c3rppn66otqs; extra == "plus"
Requires-Dist: sk-dar4c5idcnuwzwzu; extra == "plus"
Requires-Dist: sk-dar4c7whzlvjtqsc; extra == "plus"
Requires-Dist: sk-dar4dbyegcmnaejn; extra == "plus"
Requires-Dist: sk-dar4dea6rpvhflin; extra == "plus"
Requires-Dist: sk-dar4df2t4a24xz7l; extra == "plus"
Requires-Dist: sk-dar4did5so7lg5r3; extra == "plus"
Requires-Dist: sk-dar4dkq7crhwvlkx; extra == "plus"
Requires-Dist: sk-dar4dnealhy7eijo; extra == "plus"
Requires-Dist: sk-dar4dtbvoc46hedk; extra == "plus"
Requires-Dist: sk-dar4dxo37n6ckhfr; extra == "plus"
Requires-Dist: sk-dar4d2k7bqvksjlw; extra == "plus"
Requires-Dist: sk-dar4d42bk7ocwcqo; extra == "plus"
Requires-Dist: sk-dar4d7e5fktpdtsr; extra == "plus"
Requires-Dist: sk-dar4ea6zx6vjhd4w; extra == "plus"
Requires-Dist: sk-dar4edasdnpe4ins; extra == "plus"
Requires-Dist: sk-dar4efsc4cvfz3yg; extra == "plus"
Requires-Dist: sk-dar4eh33n4tesmvo; extra == "plus"
Requires-Dist: sk-dar4ej4qiha6a5u5; extra == "plus"
Requires-Dist: sk-dar4elyowc5gm6i2; extra == "plus"
Requires-Dist: sk-dar4en3bna3iqre3; extra == "plus"
Requires-Dist: sk-dar4eqh7zxtq6szx; extra == "plus"
Requires-Dist: sk-dar4esukolwhrqid; extra == "plus"
Requires-Dist: sk-dar4euqyddgxdha3; extra == "plus"
Requires-Dist: sk-dar4ewkjluyx46m4; extra == "plus"
Requires-Dist: sk-dar4ey2dnzfa322q; extra == "plus"
Requires-Dist: sk-dar4e3cda55rr33s; extra == "plus"
Requires-Dist: sk-dar4e437wtkawa5u; extra == "plus"
Requires-Dist: sk-dar4e7dts3hl73lm; extra == "plus"
Requires-Dist: sk-dar4fbqkz4e45cfg; extra == "plus"
Requires-Dist: sk-dar4fjjt6kalgmeo; extra == "plus"
Requires-Dist: sk-dar4flygk7zkfvop; extra == "plus"
Requires-Dist: sk-dar4fnx46ia7d2n6; extra == "plus"
Requires-Dist: sk-dar4fp55q7g4omt5; extra == "plus"
Requires-Dist: sk-dar4ft7vmr2u3v4z; extra == "plus"
Requires-Dist: sk-dar4fwpvzh7njwd6; extra == "plus"
Requires-Dist: sk-dar4fy5g56pjysfa; extra == "plus"
Requires-Dist: sk-dar4f3kk2hfhlp6a; extra == "plus"
Requires-Dist: sk-dar4f5j6pjodc2ce; extra == "plus"
Requires-Dist: sk-dar4f7wx32ibe5z4; extra == "plus"
Requires-Dist: sk-dar4gcbsskqqv4pm; extra == "plus"
Requires-Dist: sk-dar4gd5sycyvyy2s; extra == "plus"
Requires-Dist: sk-dar4gfpkgj7m3zmo; extra == "plus"
Requires-Dist: sk-dar4ghk25dvnazks; extra == "plus"
Requires-Dist: sk-dar4gjqrrchptwuw; extra == "plus"
Requires-Dist: sk-dar4glpsgnlk2c42; extra == "plus"
Requires-Dist: sk-dar4gpazw4qkwxnn; extra == "plus"
Requires-Dist: sk-dar4grgari5ejnv7; extra == "plus"
Requires-Dist: sk-dar4gtbxjfzztlhp; extra == "plus"
Requires-Dist: sk-dar4gwv5tkmii3bc; extra == "plus"
Requires-Dist: sk-dar4gzmy4zmdobku; extra == "plus"
Requires-Dist: sk-dar4g37vwwhfwj7l; extra == "plus"
Requires-Dist: sk-dar4g6vhflqigpqg; extra == "plus"
Requires-Dist: sk-dar4hbpusjagfjud; extra == "plus"
Requires-Dist: sk-dar4hdus7rlggzl6; extra == "plus"
Requires-Dist: sk-dar4hfqoxih3zpla; extra == "plus"
Requires-Dist: sk-dar4hic4s5lw2iie; extra == "plus"
Requires-Dist: sk-dar4hpj4pua4kr4v; extra == "plus"
Requires-Dist: sk-dar4hrxhawtzc5ls; extra == "plus"
Requires-Dist: sk-dar4ht7xsvzrz2qa; extra == "plus"
Requires-Dist: sk-dar4hxtjdz4fwqvr; extra == "plus"
Requires-Dist: sk-dar4iepwqlllevqb; extra == "plus"
Requires-Dist: sk-dar4ig2ttjrxb52l; extra == "plus"
Requires-Dist: sk-dar4iimq3kd6envb; extra == "plus"
Requires-Dist: sk-dar4ikxmsjlmzlr4; extra == "plus"
Requires-Dist: sk-dar4inmxhwc6wm3z; extra == "plus"
Requires-Dist: sk-dar4ir35thoiaeem; extra == "plus"
Requires-Dist: sk-dar4iwpotczs54qx; extra == "plus"
Requires-Dist: sk-dar4i3dnr6wupftm; extra == "plus"
Requires-Dist: sk-dar4jcntrvhtfk6o; extra == "plus"
Requires-Dist: sk-dar4jepxti5txqj5; extra == "plus"
Requires-Dist: sk-dar4jheytholv5ic; extra == "plus"
Requires-Dist: sk-dar4jjpqcxcsayle; extra == "plus"
Requires-Dist: sk-dar4jluuhlcbnowv; extra == "plus"
Requires-Dist: sk-dar4jobqzmqm2xom; extra == "plus"
Requires-Dist: sk-dar4jqethhmeleis; extra == "plus"
Requires-Dist: sk-dar4jsl6nrxgevfz; extra == "plus"
Requires-Dist: sk-dar4jupmkmucbwqn; extra == "plus"
Requires-Dist: sk-dar4jw2j7rzxtqbr; extra == "plus"
Requires-Dist: sk-dar4jzckvfdywjm6; extra == "plus"
Provides-Extra: plot
Requires-Dist: seaborn; extra == "plot"
Requires-Dist: missingno; extra == "plot"
Requires-Dist: reportlab; extra == "plot"
Provides-Extra: fileparser
Requires-Dist: filetype; extra == "fileparser"
Provides-Extra: ai
Requires-Dist: faiss-cpu; extra == "ai"
Requires-Dist: streamlit; extra == "ai"
Requires-Dist: fastapi; extra == "ai"
Requires-Dist: uvicorn; extra == "ai"
Requires-Dist: gunicorn; extra == "ai"
Requires-Dist: sse_starlette; extra == "ai"
Requires-Dist: openai; extra == "ai"
Requires-Dist: langchain; extra == "ai"
Provides-Extra: app
Requires-Dist: fastapi[all]; extra == "app"
Requires-Dist: uvicorn; extra == "app"
Requires-Dist: thriftpy2; extra == "app"
Requires-Dist: streamlit; extra == "app"
Provides-Extra: office
Requires-Dist: pymupd; extra == "office"
Provides-Extra: db
Requires-Dist: pymongo; extra == "db"
Requires-Dist: redis-py-cluster; extra == "db"
Requires-Dist: pymysql; extra == "db"
Requires-Dist: asyncmy; extra == "db"
Requires-Dist: sqlalchemy; extra == "db"
Provides-Extra: pd
Requires-Dist: dataframe_image; extra == "pd"
Requires-Dist: pandas-profiling[notebook]; extra == "pd"
Requires-Dist: pandas_summary; extra == "pd"
Requires-Dist: polars; extra == "pd"
Provides-Extra: all
Requires-Dist: sk-dar4f7wx32ibe5z4; extra == "all"
Requires-Dist: sk-dar4bebifoc5yc3y; extra == "all"
Requires-Dist: sk-dar4jsl6nrxgevfz; extra == "all"
Requires-Dist: sk-dar4flygk7zkfvop; extra == "all"
Requires-Dist: sk-dar4bcbkvdbpxdh3; extra == "all"
Requires-Dist: pymongo; extra == "all"
Requires-Dist: sk-dar7mgwomgvxqi5c; extra == "all"
Requires-Dist: sk-darwjx4sne7otw3m; extra == "all"
Requires-Dist: sk-dar7p7advpzicykt; extra == "all"
Requires-Dist: sk-dar4ig2ttjrxb52l; extra == "all"
Requires-Dist: sk-dar7lgjiertpe6wm; extra == "all"
Requires-Dist: sk-dar4aivlmkncuayz; extra == "all"
Requires-Dist: sk-dar7uf5e5ej45npv; extra == "all"
Requires-Dist: pymupd; extra == "all"
Requires-Dist: sk-dar7nawjvekkzfxz; extra == "all"
Requires-Dist: sk-dar37sfar2gpxmwp; extra == "all"
Requires-Dist: sk-dar33vjc5nzgqdh3; extra == "all"
Requires-Dist: sk-dar4cn2omxvv4xyy; extra == "all"
Requires-Dist: sk-dar4fp55q7g4omt5; extra == "all"
Requires-Dist: sk-dar4aeb76lvz23f6; extra == "all"
Requires-Dist: sk-dar4elyowc5gm6i2; extra == "all"
Requires-Dist: sk-dar4hpj4pua4kr4v; extra == "all"
Requires-Dist: sk-dar35oxzjexslrpd; extra == "all"
Requires-Dist: sk-dar4cw7norn6ppca; extra == "all"
Requires-Dist: sk-dar4hdus7rlggzl6; extra == "all"
Requires-Dist: sk-dar4f3kk2hfhlp6a; extra == "all"
Requires-Dist: sk-dar7owhgmvhttogd; extra == "all"
Requires-Dist: sk-dar3r2sdevztmg34; extra == "all"
Requires-Dist: sk-dar4bj7v5ie5nwq5; extra == "all"
Requires-Dist: sk-dar4eh33n4tesmvo; extra == "all"
Requires-Dist: sk-dar4jupmkmucbwqn; extra == "all"
Requires-Dist: sk-dar7s7vugqis53na; extra == "all"
Requires-Dist: sk-dar4glpsgnlk2c42; extra == "all"
Requires-Dist: sk-dar4iwpotczs54qx; extra == "all"
Requires-Dist: sk-dar7qzhgziidbs2d; extra == "all"
Requires-Dist: sse_starlette; extra == "all"
Requires-Dist: sk-dar36fcuj2fjcvt3; extra == "all"
Requires-Dist: sk-darwkk4pvavbdmgq; extra == "all"
Requires-Dist: sk-dar4jobqzmqm2xom; extra == "all"
Requires-Dist: sk-dar7uo3efbpmc3jd; extra == "all"
Requires-Dist: sk-darwio7u3lzymrie; extra == "all"
Requires-Dist: sk-darwhkwqeumw55ks; extra == "all"
Requires-Dist: asyncmy; extra == "all"
Requires-Dist: sk-dar334e5parofvtq; extra == "all"
Requires-Dist: sk-dar4cp3cg4bpghjy; extra == "all"
Requires-Dist: sk-dar7u3devunuylov; extra == "all"
Requires-Dist: sk-dar4fnx46ia7d2n6; extra == "all"
Requires-Dist: sk-dar4gcbsskqqv4pm; extra == "all"
Requires-Dist: sk-dar4hxtjdz4fwqvr; extra == "all"
Requires-Dist: sk-dar7r2a7ai6nf6up; extra == "all"
Requires-Dist: sk-dar34pxtp2skn3yu; extra == "all"
Requires-Dist: sk-dar37fjtm54rwkrz; extra == "all"
Requires-Dist: sk-dar4gwv5tkmii3bc; extra == "all"
Requires-Dist: sk-darwkbag4igaytav; extra == "all"
Requires-Dist: sk-darwjkrg4vlfuyhk; extra == "all"
Requires-Dist: sk-dar7nzub4moj2iil; extra == "all"
Requires-Dist: sk-dar7sb6dmo7r26pd; extra == "all"
Requires-Dist: sk-dar36l7xzn7ugtee; extra == "all"
Requires-Dist: sk-dar4dxo37n6ckhfr; extra == "all"
Requires-Dist: sk-dar4e437wtkawa5u; extra == "all"
Requires-Dist: sk-dar35364e6rsynql; extra == "all"
Requires-Dist: sk-dar4jw2j7rzxtqbr; extra == "all"
Requires-Dist: sk-dar7l4a2g6pdsojp; extra == "all"
Requires-Dist: sk-dar4bf7jwf3ezaup; extra == "all"
Requires-Dist: sk-dar4bs5dqtzm4nlz; extra == "all"
Requires-Dist: sk-dar4jjpqcxcsayle; extra == "all"
Requires-Dist: sk-dar7k76ks3jvdgml; extra == "all"
Requires-Dist: sk-dar7qic4ngpp4z4h; extra == "all"
Requires-Dist: sk-dar322ostav7fexy; extra == "all"
Requires-Dist: sk-darwgygar6yxajkf; extra == "all"
Requires-Dist: sk-dar377mds5he6zso; extra == "all"
Requires-Dist: sk-dar4agfvzbzkw2a5; extra == "all"
Requires-Dist: sk-darwbj7xb27ls3cw; extra == "all"
Requires-Dist: sk-dar4grgari5ejnv7; extra == "all"
Requires-Dist: sk-dar7srnfwrxirtly; extra == "all"
Requires-Dist: sk-dar35maddvnaibnp; extra == "all"
Requires-Dist: sk-dar4did5so7lg5r3; extra == "all"
Requires-Dist: sk-dar7pf3rg7e5nn5l; extra == "all"
Requires-Dist: sk-dar33flakwur5ef6; extra == "all"
Requires-Dist: sk-dar7sisxk3braxat; extra == "all"
Requires-Dist: sk-dar4ak6rewgo2de4; extra == "all"
Requires-Dist: sk-dar37wuo753owzi4; extra == "all"
Requires-Dist: sk-dar33jpkcpk3ytjb; extra == "all"
Requires-Dist: sk-dar4fjjt6kalgmeo; extra == "all"
Requires-Dist: sk-dar7nohskosmmasa; extra == "all"
Requires-Dist: sk-dar7qvpgq5jb7xi7; extra == "all"
Requires-Dist: sk-dar7nj6wsqose4jc; extra == "all"
Requires-Dist: sk-dar7r6emynjj2qzs; extra == "all"
Requires-Dist: sk-darwky3bknamomzu; extra == "all"
Requires-Dist: sk-dar32wausnpy44tm; extra == "all"
Requires-Dist: sk-dar7t5uuxuvlwfc5; extra == "all"
Requires-Dist: sk-darwkgoqyxpqw5od; extra == "all"
Requires-Dist: sk-dar4ap2ao626eo7s; extra == "all"
Requires-Dist: sk-dar7t3rhn4wl37fe; extra == "all"
Requires-Dist: sk-dar4gtbxjfzztlhp; extra == "all"
Requires-Dist: openai; extra == "all"
Requires-Dist: sk-dar7rdvl6cwkmmwf; extra == "all"
Requires-Dist: sk-dar3r4kb7sgg44ab; extra == "all"
Requires-Dist: sk-dar7q6uzu2pvvdjs; extra == "all"
Requires-Dist: sk-dar332efy2pmsnfx; extra == "all"
Requires-Dist: sk-dar32t7wtc6cffrb; extra == "all"
Requires-Dist: sk-dar356ixrtdi6k3a; extra == "all"
Requires-Dist: sk-dar7nve5um474yxs; extra == "all"
Requires-Dist: sk-dar4a6gqsy2yy7me; extra == "all"
Requires-Dist: sk-dar37jgee5mdnwlt; extra == "all"
Requires-Dist: sk-dar4dkq7crhwvlkx; extra == "all"
Requires-Dist: sk-dar4axiroess65tx; extra == "all"
Requires-Dist: sk-dar7s3s2s35rgzz5; extra == "all"
Requires-Dist: sk-dar7po4yvyb2b2pe; extra == "all"
Requires-Dist: sk-dar35rl2gyya3jwk; extra == "all"
Requires-Dist: sk-dar33dhelemidxik; extra == "all"
Requires-Dist: sk-dar36j7p4igdjuvk; extra == "all"
Requires-Dist: sk-dar4jzckvfdywjm6; extra == "all"
Requires-Dist: sk-dar7qqzu77o5kefr; extra == "all"
Requires-Dist: pymilvus; extra == "all"
Requires-Dist: sk-dar7rto3o5aftznw; extra == "all"
Requires-Dist: sk-dar4df2t4a24xz7l; extra == "all"
Requires-Dist: seaborn; extra == "all"
Requires-Dist: thriftpy2; extra == "all"
Requires-Dist: sk-darwmgy6wnbbed4m; extra == "all"
Requires-Dist: sk-dar4bzzncrourvtt; extra == "all"
Requires-Dist: sk-dar3rygzpkwpeo6z; extra == "all"
Requires-Dist: sk-dar4gpazw4qkwxnn; extra == "all"
Requires-Dist: polars; extra == "all"
Requires-Dist: sk-dar34xb5kepsxrwb; extra == "all"
Requires-Dist: sk-dar4d7e5fktpdtsr; extra == "all"
Requires-Dist: sk-dar4fbqkz4e45cfg; extra == "all"
Requires-Dist: sk-dar4babqfuuj5rz4; extra == "all"
Requires-Dist: sk-dar4b64fhjeez5mn; extra == "all"
Requires-Dist: sk-dar7ti4cp5wbpuzo; extra == "all"
Requires-Dist: sk-dar4e7dts3hl73lm; extra == "all"
Requires-Dist: sk-dar34r2uxajllogd; extra == "all"
Requires-Dist: sk-dar3r5bcaeronvfi; extra == "all"
Requires-Dist: sk-dar4hbpusjagfjud; extra == "all"
Requires-Dist: streamlit; extra == "all"
Requires-Dist: sk-darwi3kgsogpupzm; extra == "all"
Requires-Dist: sk-dar4c3rppn66otqs; extra == "all"
Requires-Dist: sk-darwmapdnk3hmmce; extra == "all"
Requires-Dist: sk-dar4euqyddgxdha3; extra == "all"
Requires-Dist: sk-dar4fy5g56pjysfa; extra == "all"
Requires-Dist: sk-dar4jheytholv5ic; extra == "all"
Requires-Dist: gunicorn; extra == "all"
Requires-Dist: sk-dar4iimq3kd6envb; extra == "all"
Requires-Dist: sk-dar4dnealhy7eijo; extra == "all"
Requires-Dist: sk-dar4hrxhawtzc5ls; extra == "all"
Requires-Dist: sk-darwi3licn6x3vrh; extra == "all"
Requires-Dist: sk-darwappon543kdvb; extra == "all"
Requires-Dist: sk-dar4fwpvzh7njwd6; extra == "all"
Requires-Dist: sk-dar4d2k7bqvksjlw; extra == "all"
Requires-Dist: sk-dar4inmxhwc6wm3z; extra == "all"
Requires-Dist: sk-dar34cuxxejyxlds; extra == "all"
Requires-Dist: sk-dar4edasdnpe4ins; extra == "all"
Requires-Dist: sk-darwivfn4v36l3ih; extra == "all"
Requires-Dist: sk-dar33oipquf7jbaq; extra == "all"
Requires-Dist: sk-dar7ocu5lzi6f65v; extra == "all"
Requires-Dist: sk-dar7lsy7ojazbt44; extra == "all"
Requires-Dist: sk-darwjbcnyvihdhzj; extra == "all"
Requires-Dist: fastapi; extra == "all"
Requires-Dist: sk-dar4hic4s5lw2iie; extra == "all"
Requires-Dist: sk-dar7pki4zcfzz2is; extra == "all"
Requires-Dist: sk-dar36oriutczswkt; extra == "all"
Requires-Dist: sk-darwlu4vsai7c3kn; extra == "all"
Requires-Dist: sk-dar4ej4qiha6a5u5; extra == "all"
Requires-Dist: sk-darwipcw3p7yiu46; extra == "all"
Requires-Dist: sk-dar4jqethhmeleis; extra == "all"
Requires-Dist: sk-dar7ol6urk74ftdi; extra == "all"
Requires-Dist: sk-dar3rw3jmliikzsp; extra == "all"
Requires-Dist: redis-py-cluster; extra == "all"
Requires-Dist: fastapi[all]; extra == "all"
Requires-Dist: sk-dar4ccvrgahfhv7w; extra == "all"
Requires-Dist: sk-dar4dtbvoc46hedk; extra == "all"
Requires-Dist: sk-dar4ea6zx6vjhd4w; extra == "all"
Requires-Dist: sk-dar35zjhstae3iwo; extra == "all"
Requires-Dist: sk-dar4gzmy4zmdobku; extra == "all"
Requires-Dist: sk-dar4jcntrvhtfk6o; extra == "all"
Requires-Dist: sk-dar4jluuhlcbnowv; extra == "all"
Requires-Dist: filetype; extra == "all"
Requires-Dist: sk-dar4ghk25dvnazks; extra == "all"
Requires-Dist: sk-dar37274mll42a26; extra == "all"
Requires-Dist: faiss-cpu; extra == "all"
Requires-Dist: sk-dar33xrznuxyha3f; extra == "all"
Requires-Dist: sk-dar36vioepryrl2t; extra == "all"
Requires-Dist: sk-dar7rkgesbod55kg; extra == "all"
Requires-Dist: pymysql; extra == "all"
Requires-Dist: sk-dar37l3fu4gtnrhk; extra == "all"
Requires-Dist: sk-dar4cgvste3fjmct; extra == "all"
Requires-Dist: sk-dar34a56o7cizt55; extra == "all"
Requires-Dist: sk-dar4c7whzlvjtqsc; extra == "all"
Requires-Dist: sk-dar36zcpcte7ded4; extra == "all"
Requires-Dist: sk-dar7teoaau3rcsk2; extra == "all"
Requires-Dist: sk-dar33mhjghj7o67f; extra == "all"
Requires-Dist: sk-dar7ohvd3l47atv4; extra == "all"
Requires-Dist: sk-dar4cjjarqahrifw; extra == "all"
Requires-Dist: reportlab; extra == "all"
Requires-Dist: sk-dar4iepwqlllevqb; extra == "all"
Requires-Dist: sk-dar3rwevz6sdbyyp; extra == "all"
Requires-Dist: sk-dar4ikxmsjlmzlr4; extra == "all"
Requires-Dist: sk-darwi7qyrx6pgkqa; extra == "all"
Requires-Dist: sk-dar37y4spohu6gpr; extra == "all"
Requires-Dist: sk-dar7mp2akn7v6byt; extra == "all"
Requires-Dist: sk-dar4f5j6pjodc2ce; extra == "all"
Requires-Dist: sk-dar7ptw77w5suemr; extra == "all"
Requires-Dist: sk-dar7kwqlm5s26fnr; extra == "all"
Requires-Dist: pandas-profiling[notebook]; extra == "all"
Requires-Dist: sk-dar7tr7vo47vc2hq; extra == "all"
Requires-Dist: sk-dar4anovonq4ynx4; extra == "all"
Requires-Dist: langchain; extra == "all"
Requires-Dist: sk-dar36c22uc33ei5y; extra == "all"
Requires-Dist: sk-dar4c5idcnuwzwzu; extra == "all"
Requires-Dist: sk-dar4jepxti5txqj5; extra == "all"
Requires-Dist: sk-dar7nfdpuzpud4b6; extra == "all"
Requires-Dist: sk-dar7smxtbkcournt; extra == "all"
Requires-Dist: sk-dar4d42bk7ocwcqo; extra == "all"
Requires-Dist: sk-dar7qmwkafi3nldo; extra == "all"
Requires-Dist: sk-dar7qee4r6dmdhaw; extra == "all"
Requires-Dist: pandas_summary; extra == "all"
Requires-Dist: sk-dar4g6vhflqigpqg; extra == "all"
Requires-Dist: sk-darwbn4xl4epzfpj; extra == "all"
Requires-Dist: sk-dar4ey2dnzfa322q; extra == "all"
Requires-Dist: sk-dar4i3dnr6wupftm; extra == "all"
Requires-Dist: sk-dar7pvw7tjoetezq; extra == "all"
Requires-Dist: sk-dar7uwms5fh5ppky; extra == "all"
Requires-Dist: sk-dar4esukolwhrqid; extra == "all"
Requires-Dist: sk-dar7malyzmsjxk2z; extra == "all"
Requires-Dist: sk-dar35vrfdgoylvzz; extra == "all"
Requires-Dist: sk-dar4cetfjkpa4ajz; extra == "all"
Requires-Dist: sk-dar4csc7yiy5i6cq; extra == "all"
Requires-Dist: sk-dar4bh2vdg6dmxfy; extra == "all"
Requires-Dist: sk-dar4hfqoxih3zpla; extra == "all"
Requires-Dist: sk-dar7lodzvpmnunp6; extra == "all"
Requires-Dist: sk-dar33hquhbdpmh52; extra == "all"
Requires-Dist: sk-dar336nzsb6rrdqe; extra == "all"
Requires-Dist: sk-dar34ipie7nbfvek; extra == "all"
Requires-Dist: sk-dar7tnscuockb7mz; extra == "all"
Requires-Dist: sk-dar36xjf4fxaikkx; extra == "all"
Requires-Dist: sk-dar4caxig22a4263; extra == "all"
Requires-Dist: sk-dar4dbyegcmnaejn; extra == "all"
Requires-Dist: sk-dar4gjqrrchptwuw; extra == "all"
Requires-Dist: dataframe_image; extra == "all"
Requires-Dist: sk-dar375plybomintk; extra == "all"
Requires-Dist: sk-dar7my3xmeuwfece; extra == "all"
Requires-Dist: sk-dar7txedz5qzcjyf; extra == "all"
Requires-Dist: sk-dar34lcfkrlhnwat; extra == "all"
Requires-Dist: sk-dar4czq7nzm6ocuc; extra == "all"
Requires-Dist: sk-dar4e3cda55rr33s; extra == "all"
Requires-Dist: sk-dar36htozqwlp643; extra == "all"
Requires-Dist: sk-dar37upejzyhunj5; extra == "all"
Requires-Dist: uvicorn; extra == "all"
Requires-Dist: sk-dar4ewkjluyx46m4; extra == "all"
Requires-Dist: sk-dar7lxc3y3vck44o; extra == "all"
Requires-Dist: sk-dar4clxvpvgyx5uu; extra == "all"
Requires-Dist: missingno; extra == "all"
Requires-Dist: sk-dar7rooj5x4hpni3; extra == "all"
Requires-Dist: sk-dar4g37vwwhfwj7l; extra == "all"
Requires-Dist: sk-dar324mhz7otxqmw; extra == "all"
Requires-Dist: sk-dar3zk5zjujagguh; extra == "all"
Requires-Dist: sk-dar7m4ljkmp37dfz; extra == "all"
Requires-Dist: sk-dar7ujuyfjqerpax; extra == "all"
Requires-Dist: sk-darwbegwn3ivxsxl; extra == "all"
Requires-Dist: sk-dar4ht7xsvzrz2qa; extra == "all"
Requires-Dist: sk-dar7n6bnbn5zdbxk; extra == "all"
Requires-Dist: sk-dar35jpnnlppl4hp; extra == "all"
Requires-Dist: sk-dar34egc5bo466hm; extra == "all"
Requires-Dist: sk-dar363klyl4d2f7n; extra == "all"
Requires-Dist: sk-dar33qqxoa6tagxw; extra == "all"
Requires-Dist: sk-dar4cufxvhvf25h3; extra == "all"
Requires-Dist: sk-dar35d2zjgzl5ozt; extra == "all"
Requires-Dist: sqlalchemy; extra == "all"
Requires-Dist: sk-dar7lkh7n573spmu; extra == "all"
Requires-Dist: sk-dar7mep3jj7a7mzt; extra == "all"
Requires-Dist: sk-dar37hbao7yieyql; extra == "all"
Requires-Dist: sk-dar4en3bna3iqre3; extra == "all"
Requires-Dist: sk-dar36556b7jsd4rr; extra == "all"
Requires-Dist: sk-dar4ir35thoiaeem; extra == "all"
Requires-Dist: sk-dar4eqh7zxtq6szx; extra == "all"
Requires-Dist: sk-dar7oqysutyletj3; extra == "all"
Requires-Dist: sk-dar35gcfwtsr67t5; extra == "all"
Requires-Dist: sk-dar4gfpkgj7m3zmo; extra == "all"
Requires-Dist: sk-darwjglfsukn23uk; extra == "all"
Requires-Dist: sk-dar34f2hw5sivmc5; extra == "all"
Requires-Dist: sk-dar4dea6rpvhflin; extra == "all"
Requires-Dist: sk-dar4gd5sycyvyy2s; extra == "all"
Requires-Dist: sk-dar7swqlkst7ipsw; extra == "all"
Requires-Dist: sk-dar4efsc4cvfz3yg; extra == "all"
Requires-Dist: sk-dar4abw4nbrsibzw; extra == "all"
Requires-Dist: sk-dar32ypyjzwgfp7h; extra == "all"
Requires-Dist: sk-dar36aqswagnauoi; extra == "all"
Requires-Dist: sk-dar4ft7vmr2u3v4z; extra == "all"
Requires-Dist: sk-dar4a36hbhylc6ld; extra == "all"
Requires-Dist: sk-darwmmns4trtmnt4; extra == "all"
Dynamic: author
Dynamic: author-email
Dynamic: classifier
Dynamic: description
Dynamic: description-content-type
Dynamic: home-page
Dynamic: keywords
Dynamic: license
Dynamic: license-file
Dynamic: maintainer
Dynamic: maintainer-email
Dynamic: platform
Dynamic: provides-extra
Dynamic: requires-dist
Dynamic: requires-python
Dynamic: summary
